Metadata-Version: 2.1
Name: covalent-aws-plugins
Version: 0.18.0rc0
Summary: Covalent AWS Plugins
Home-page: https://github.com/AgnostiqHQ/covalent-aws-plugins
Author: Agnostiq
Author-email: support@agnostiq.ai
Maintainer: Agnostiq
License: Apache License 2.0
Download-URL: https://github.com/AgnostiqHQ/covalent-aws-plugins/archive/v0.18.0.tar.gz
Platform: UNKNOWN
Classifier: Development Status :: 4 - Beta
Classifier: Environment :: Console
Classifier: Environment :: Plugins
Classifier: Intended Audience :: Developers
Classifier: Intended Audience :: Education
Classifier: Intended Audience :: Science/Research
Classifier: License :: OSI Approved :: Apache Software License
Classifier: Natural Language :: English
Classifier: Operating System :: MacOS
Classifier: Operating System :: POSIX :: Linux
Classifier: Programming Language :: Python :: 3
Classifier: Programming Language :: Python :: 3 :: Only
Classifier: Programming Language :: Python :: 3.8
Classifier: Programming Language :: Python :: 3.9
Classifier: Topic :: Adaptive Technologies
Classifier: Topic :: Scientific/Engineering
Classifier: Topic :: Scientific/Engineering :: Interface Engine/Protocol Translator
Classifier: Topic :: Software Development
Classifier: Topic :: System :: Distributed Computing
Provides-Extra: all
Provides-Extra: batch
Provides-Extra: ec2
Provides-Extra: lambda
Provides-Extra: braket
Provides-Extra: ecs
